jieba-stubs/__init__.pyi
jieba-stubs/_compat.pyi
jieba-stubs/analyse/__init__.pyi
jieba-stubs/analyse/textrank.pyi
jieba-stubs/analyse/tfidf.pyi
jieba-stubs/posseg/__init__.pyi
jieba-stubs/posseg/char_state_tab.pyi
jieba-stubs/posseg/prob_emit.pyi
jieba-stubs/posseg/prob_start.pyi
jieba-stubs/posseg/prob_trans.pyi
jieba-stubs/posseg/viterbi.pyi
types_jieba-0.0.7.dist-info/LICENSE
types_jieba-0.0.7.dist-info/METADATA
types_jieba-0.0.7.dist-info/WHEEL
types_jieba-0.0.7.dist-info/top_level.txt
types_jieba-0.0.7.dist-info/RECORD
