Metadata-Version: 2.1
Name: types-jieba
Version: 0.0.7
Summary: jieba 类型库
Author-email: thep0y <thepoy@163.com>
License: MIT License
Project-URL: homepage, https://github.com/thep0y/types-jieba
Project-URL: repository, https://github.com/thep0y/types-jieba
Keywords: jieba,中文,分词,类型
Classifier: Programming Language :: Python :: 3
Requires-Python: >=3
License-File: LICENSE
